twooter/__init__.py
twooter/cli.py
twooter/sdk.py
twooter/apiclient/__init__.py
twooter/apiclient/agent.py
twooter/apiclient/auth_api.py
twooter/apiclient/competition.py
twooter/apiclient/feeds.py
twooter/apiclient/notifications.py
twooter/apiclient/search.py
twooter/apiclient/tags.py
twooter/apiclient/twoots.py
twooter/apiclient/users.py
twooter/cli/__init__.py
twooter/cli/client.py
twooter/cli/config.py
twooter/cli/http.py
twooter/cli/parser.py
twooter/cli/runner.py
twooter/cli/storage.py
twooter/cli/util.py
twooter-1.1.0.dist-info/METADATA
twooter-1.1.0.dist-info/WHEEL
twooter-1.1.0.dist-info/entry_points.txt
twooter-1.1.0.dist-info/licenses/LICENSE
twooter-1.1.0.dist-info/RECORD
