Metadata-Version: 2.4
Name: twooter
Version: 1.1.0
Summary: CLI and SDK for interacting with the CTN CTF.
Project-URL: Homepage, https://github.com/capturethenarrative/twooter
Project-URL: Issues, https://github.com/capturethenarrative/twooter/issues
Author-email: rdttl <rdttl@proton.me>
License: MIT License
License-File: LICENSE
Keywords: ctn,twooter
Requires-Python: >=3.9
Requires-Dist: requests>=2.31.0
